{
  "users": [
    {
      "id": "ac4269e4-a4fb-4954-adc9-19eca4c43f6d",
      "full_name": "مریم پارسا",
      "gender": "Female",
      "b_date": "1994-05-18",
      "age": 31,
      "email": "mrym.prs@example.com",
      "phone": "037-32948611",
      "country": "Iran",
      "city": "کرمان",
      "latitude": "16.4145",
      "longitude": "31.2260",
      "picture_large": "https://randomuser.me/api/portraits/women/61.jpg",
      "note": "Note1...",
      "color": "#52bf85",
      "course": "Statistics",
      "favorite": false
    },
    {
      "id": "1d09271c-b80d-409a-a4c7-da4176ec4880",
      "full_name": "Adna Moraes",
      "gender": "Female",
      "b_date": "1993-12-30",
      "age": 31,
      "email": "adna.moraes@example.com",
      "phone": "(16) 5360-0193",
      "country": "Brazil",
      "city": "João Pessoa",
      "latitude": "32.3396",
      "longitude": "-114.9154",
      "picture_large": "https://randomuser.me/api/portraits/women/73.jpg",
      "note": "Note1...",
      "color": "#bd9a41",
      "course": "Law",
      "favorite": false
    },
    {
      "id": "d6c2995a-001f-45c0-8314-7d7151af53f1",
      "full_name": "Buse Koçoğlu",
      "gender": "Female",
      "b_date": "1948-01-22",
      "age": 77,
      "email": "buse.kocoglu@example.com",
      "phone": "(432)-755-4245",
      "country": "Turkey",
      "city": "Adıyaman",
      "latitude": "67.4825",
      "longitude": "26.2511",
      "picture_large": "https://randomuser.me/api/portraits/women/78.jpg",
      "note": "Note1...",
      "color": "#c512e3",
      "course": "Chess",
      "favorite": false
    },
    {
      "id": "fef28e9f-5057-4482-a402-7a36e05d754b",
      "full_name": "Ross Mckinney",
      "gender": "Male",
      "b_date": "1961-07-29",
      "age": 64,
      "email": "ross.mckinney@example.com",
      "phone": "05-4055-7194",
      "country": "Australia",
      "city": "Hervey Bay",
      "latitude": "-61.6385",
      "longitude": "-48.4668",
      "picture_large": "https://randomuser.me/api/portraits/men/45.jpg",
      "note": "Note1...",
      "color": "#447936",
      "course": "Chemistry",
      "favorite": true
    },
    {
      "id": "6d82bbca-2881-41f8-8094-5fea8f5c3d28",
      "full_name": "Linda Roberts",
      "gender": "Female",
      "b_date": "1980-03-25",
      "age": 45,
      "email": "linda.roberts@example.com",
      "phone": "(926) 724-9868",
      "country": "United States",
      "city": "Pittsburgh",
      "latitude": "-40.0918",
      "longitude": "9.2141",
      "picture_large": "https://randomuser.me/api/portraits/women/6.jpg",
      "note": "Note1...",
      "color": "#f051ae",
      "course": "Chess",
      "favorite": false
    },
    {
      "id": "b54c401e-3507-4a61-b901-dabac80a0a15",
      "full_name": "Ellen Linna",
      "gender": "Female",
      "b_date": "1970-08-04",
      "age": 55,
      "email": "ellen.linna@example.com",
      "phone": "03-275-393",
      "country": "Finland",
      "city": "Akaa",
      "latitude": "-60.9073",
      "longitude": "126.7213",
      "picture_large": "https://randomuser.me/api/portraits/women/36.jpg",
      "note": "Note1...",
      "color": "#ec6e7d",
      "course": "Medicine",
      "favorite": true
    },
    {
      "id": "d445c8e4-014b-4d29-bc0b-f2cbc2b265e6",
      "full_name": "Élise Henry",
      "gender": "Female",
      "b_date": "1989-10-03",
      "age": 36,
      "email": "elise.henry@example.com",
      "phone": "079 942 19 85",
      "country": "Switzerland",
      "city": "Küssnacht (Sz)",
      "latitude": "62.3097",
      "longitude": "92.2200",
      "picture_large": "https://randomuser.me/api/portraits/women/92.jpg",
      "note": "Note1...",
      "color": "#ac1871",
      "course": "Chess",
      "favorite": true
    },
    {
      "id": "624498c1-9c83-4f87-a1b7-5cebda0e966e",
      "full_name": "Necati Ertürk",
      "gender": "Male",
      "b_date": "1998-05-21",
      "age": 27,
      "email": "necati.erturk@example.com",
      "phone": "(582)-567-7286",
      "country": "Turkey",
      "city": "Zonguldak",
      "latitude": "71.5483",
      "longitude": "-165.8365",
      "picture_large": "https://randomuser.me/api/portraits/men/48.jpg",
      "note": "Note1...",
      "color": "#730947",
      "course": "Physics",
      "favorite": false
    },
    {
      "id": "23cf0656-55fd-4735-afde-d1ebc0062609",
      "full_name": "Nihal Akar",
      "gender": "Male",
      "b_date": "1981-01-02",
      "age": 44,
      "email": "nihal.akar@example.com",
      "phone": "(380)-887-8357",
      "country": "Turkey",
      "city": "Bursa",
      "latitude": "-11.6535",
      "longitude": "-113.7978",
      "picture_large": "https://randomuser.me/api/portraits/men/24.jpg",
      "note": "Note1...",
      "color": "#ab1431",
      "course": "Physics",
      "favorite": false
    },
    {
      "id": "eb8fc623-c926-4c78-bb5e-4e695432905c",
      "full_name": "Katerina Slota",
      "gender": "Female",
      "b_date": "1970-08-30",
      "age": 55,
      "email": "katerina.slota@example.com",
      "phone": "(066) B68-4113",
      "country": "Ukraine",
      "city": "Pervomayskiy",
      "latitude": "3.2454",
      "longitude": "101.0270",
      "picture_large": "https://randomuser.me/api/portraits/women/9.jpg",
      "note": "Note1...",
      "color": "#cc133f",
      "course": "Statistics",
      "favorite": false
    },
    {
      "id": "6479e824-6faf-4550-8d97-2d7b2d921b53",
      "full_name": "Snežana Radosavljević",
      "gender": "Female",
      "b_date": "1956-08-28",
      "age": 69,
      "email": "snezana.radosavljevic@example.com",
      "phone": "037-7891-900",
      "country": "Serbia",
      "city": "Topola",
      "latitude": "1.3469",
      "longitude": "14.4756",
      "picture_large": "https://randomuser.me/api/portraits/women/58.jpg",
      "note": "Note1...",
      "color": "#61658f",
      "course": "Chemistry",
      "favorite": false
    },
    {
      "id": "69f43796-098b-41e7-91ee-779bc3296e55",
      "full_name": "فاطمه کوتی",
      "gender": "Female",
      "b_date": "1984-04-18",
      "age": 41,
      "email": "ftmh.khwty@example.com",
      "phone": "080-36985956",
      "country": "Iran",
      "city": "ارومیه",
      "latitude": "-15.6883",
      "longitude": "7.9130",
      "picture_large": "https://randomuser.me/api/portraits/women/62.jpg",
      "note": "Note1...",
      "color": "#d5dda0",
      "course": "Chemistry",
      "favorite": false
    },
    {
      "id": "9ce2b109-db25-443e-903e-ece90f40b018",
      "full_name": "Ludwig Rolland",
      "gender": "Male",
      "b_date": "1964-05-07",
      "age": 61,
      "email": "ludwig.rolland@example.com",
      "phone": "075 944 62 61",
      "country": "Switzerland",
      "city": "Menziken",
      "latitude": "38.4919",
      "longitude": "99.7481",
      "picture_large": "https://randomuser.me/api/portraits/men/10.jpg",
      "note": "Note1...",
      "color": "#4f12ae",
      "course": "Dancing",
      "favorite": true
    },
    {
      "id": "0fcff9ce-4e9a-4612-a295-1791248a61e4",
      "full_name": "Babür Karaböcek",
      "gender": "Male",
      "b_date": "1968-09-27",
      "age": 57,
      "email": "babur.karabocek@example.com",
      "phone": "(057)-817-4745",
      "country": "Turkey",
      "city": "Eskişehir",
      "latitude": "-43.0271",
      "longitude": "-102.8575",
      "picture_large": "https://randomuser.me/api/portraits/men/66.jpg",
      "note": "Note1...",
      "color": "#269490",
      "course": "Mathematics",
      "favorite": false
    },
    {
      "id": "37fc9d50-bd47-4e8e-9c5e-133094582840",
      "full_name": "Calvino Rezende",
      "gender": "Male",
      "b_date": "1983-06-22",
      "age": 42,
      "email": "calvino.rezende@example.com",
      "phone": "(19) 7414-1735",
      "country": "Brazil",
      "city": "Carapicuíba",
      "latitude": "24.8663",
      "longitude": "85.7904",
      "picture_large": "https://randomuser.me/api/portraits/men/42.jpg",
      "note": "Note1...",
      "color": "#d850df",
      "course": "Medicine",
      "favorite": true
    },
    {
      "id": "07d9a7f2-adbf-42e5-b763-3b85f58947f2",
      "full_name": "Bozena Habermann",
      "gender": "Female",
      "b_date": "1998-01-16",
      "age": 27,
      "email": "bozena.habermann@example.com",
      "phone": "0825-4273527",
      "country": "Germany",
      "city": "Treuen",
      "latitude": "-56.8439",
      "longitude": "168.6799",
      "picture_large": "https://randomuser.me/api/portraits/women/31.jpg",
      "note": "Note1...",
      "color": "#cabd0b",
      "course": "English",
      "favorite": false
    },
    {
      "id": "50c29474-add7-4128-8dbf-2642244c4fe2",
      "full_name": "Tony Lemoine",
      "gender": "Male",
      "b_date": "2000-03-02",
      "age": 25,
      "email": "tony.lemoine@example.com",
      "phone": "04-99-25-85-14",
      "country": "France",
      "city": "Argenteuil",
      "latitude": "68.9488",
      "longitude": "82.4233",
      "picture_large": "https://randomuser.me/api/portraits/men/71.jpg",
      "note": "Note1...",
      "color": "#e31f9f",
      "course": "Dancing",
      "favorite": true
    },
    {
      "id": "742fd88e-11ea-43aa-a3c0-46020d2b6281",
      "full_name": "Arianna Fields",
      "gender": "Female",
      "b_date": "1986-07-05",
      "age": 39,
      "email": "arianna.fields@example.com",
      "phone": "04-9309-6264",
      "country": "Australia",
      "city": "Perth",
      "latitude": "58.9362",
      "longitude": "144.0388",
      "picture_large": "https://randomuser.me/api/portraits/women/19.jpg",
      "note": "Note1...",
      "color": "#48c4d0",
      "course": "English",
      "favorite": false
    },
    {
      "id": "fc31f880-806f-4cf6-b8d4-8abb3dabda74",
      "full_name": "Sophia Nguyen",
      "gender": "Female",
      "b_date": "1951-08-09",
      "age": 74,
      "email": "sophia.nguyen@example.com",
      "phone": "05-9304-4920",
      "country": "Australia",
      "city": "Mackay",
      "latitude": "58.6600",
      "longitude": "63.0624",
      "picture_large": "https://randomuser.me/api/portraits/women/11.jpg",
      "note": "Note1...",
      "color": "#4aee5a",
      "course": "Chemistry",
      "favorite": true
    },
    {
      "id": "4a1e3c08-2031-4aa2-8ac5-13f20ba736e0",
      "full_name": "Navami Chavare",
      "gender": "Female",
      "b_date": "1946-01-24",
      "age": 79,
      "email": "navami.chavare@example.com",
      "phone": "8116253686",
      "country": "India",
      "city": "Bareilly",
      "latitude": "38.2106",
      "longitude": "117.6904",
      "picture_large": "https://randomuser.me/api/portraits/women/27.jpg",
      "note": "Note1...",
      "color": "#98981d",
      "course": "English",
      "favorite": false
    },
    {
      "id": "bd58bc06-3fc7-4c89-bc6c-5702ad9a011c",
      "full_name": "Fatih Çetiner",
      "gender": "Male",
      "b_date": "1964-12-11",
      "age": 60,
      "email": "fatih.cetiner@example.com",
      "phone": "(694)-758-8852",
      "country": "Turkey",
      "city": "Erzurum",
      "latitude": "56.9364",
      "longitude": "132.5903",
      "picture_large": "https://randomuser.me/api/portraits/men/23.jpg",
      "note": "Note1...",
      "color": "#507da5",
      "course": "Dancing",
      "favorite": true
    },
    {
      "id": "ad4ee7c1-119d-4712-9e34-29c51279ec7c",
      "full_name": "Väinö Pulli",
      "gender": "Male",
      "b_date": "1950-01-05",
      "age": 75,
      "email": "vaino.pulli@example.com",
      "phone": "07-762-493",
      "country": "Finland",
      "city": "Kustavi",
      "latitude": "-83.6229",
      "longitude": "-16.2593",
      "picture_large": "https://randomuser.me/api/portraits/men/2.jpg",
      "note": "Note1...",
      "color": "#3d8d78",
      "course": "Chess",
      "favorite": false
    },
    {
      "id": "7dc4c650-dd1f-4153-951f-7793920f81eb",
      "full_name": "Kaća Mihajlović",
      "gender": "Female",
      "b_date": "1947-04-14",
      "age": 78,
      "email": "kaca.mihajlovic@example.com",
      "phone": "011-3751-553",
      "country": "Serbia",
      "city": "Bujanovac",
      "latitude": "9.2021",
      "longitude": "42.4591",
      "picture_large": "https://randomuser.me/api/portraits/women/95.jpg",
      "note": "Note1...",
      "color": "#c3aea5",
      "course": "Statistics",
      "favorite": false
    },
    {
      "id": "b09ee84f-a3e5-4177-9259-483488efa9d3",
      "full_name": "Nevena Simeonović",
      "gender": "Female",
      "b_date": "1996-02-26",
      "age": 29,
      "email": "nevena.simeonovic@example.com",
      "phone": "039-9430-414",
      "country": "Serbia",
      "city": "Knić",
      "latitude": "41.8849",
      "longitude": "89.2096",
      "picture_large": "https://randomuser.me/api/portraits/women/20.jpg",
      "note": "Note1...",
      "color": "#8c3b77",
      "course": "English",
      "favorite": false
    },
    {
      "id": "4a19cd2b-6c68-48d0-abd8-6e8163dab93c",
      "full_name": "Larry Bishop",
      "gender": "Male",
      "b_date": "1972-10-17",
      "age": 53,
      "email": "larry.bishop@example.com",
      "phone": "06-0050-1879",
      "country": "Australia",
      "city": "Melbourne",
      "latitude": "-0.8933",
      "longitude": "-27.1955",
      "picture_large": "https://randomuser.me/api/portraits/men/93.jpg",
      "note": "Note1...",
      "color": "#ab4e95",
      "course": "English",
      "favorite": false
    },
    {
      "id": "ccbd4ade-ddba-4562-bc61-71c5937bca19",
      "full_name": "Rosina Opanasenko",
      "gender": "Female",
      "b_date": "1963-09-06",
      "age": 62,
      "email": "rosina.opanasenko@example.com",
      "phone": "(099) L68-1974",
      "country": "Ukraine",
      "city": "Derazhnya",
      "latitude": "36.9575",
      "longitude": "-31.2198",
      "picture_large": "https://randomuser.me/api/portraits/women/93.jpg",
      "note": "Note1...",
      "color": "#274c75",
      "course": "Chess",
      "favorite": true
    },
    {
      "id": "2ca3a611-7170-43a2-8e80-1dd7892d4d31",
      "full_name": "Berta Fogaça",
      "gender": "Female",
      "b_date": "1996-07-22",
      "age": 29,
      "email": "berta.fogaca@example.com",
      "phone": "(38) 5637-1045",
      "country": "Brazil",
      "city": "Belford Roxo",
      "latitude": "-1.0856",
      "longitude": "123.9201",
      "picture_large": "https://randomuser.me/api/portraits/women/13.jpg",
      "note": "Note1...",
      "color": "#709239",
      "course": "Law",
      "favorite": true
    },
    {
      "id": "ddc92074-d06f-49ea-816c-cad0369ecbef",
      "full_name": "Nelson Lawson",
      "gender": "Male",
      "b_date": "1984-02-04",
      "age": 41,
      "email": "nelson.lawson@example.com",
      "phone": "(784) 778-1551",
      "country": "United States",
      "city": "Oklahoma City",
      "latitude": "2.4149",
      "longitude": "96.3089",
      "picture_large": "https://randomuser.me/api/portraits/men/42.jpg",
      "note": "Note1...",
      "color": "#b06ff9",
      "course": "Chess",
      "favorite": false
    },
    {
      "id": "00f89564-e923-4957-922d-9a9ee9cd15bc",
      "full_name": "Diogo Peixoto",
      "gender": "Male",
      "b_date": "1984-05-12",
      "age": 41,
      "email": "diogo.peixoto@example.com",
      "phone": "(37) 8153-2740",
      "country": "Brazil",
      "city": "Várzea Paulista",
      "latitude": "-66.5348",
      "longitude": "176.1334",
      "picture_large": "https://randomuser.me/api/portraits/men/35.jpg",
      "note": "Note1...",
      "color": "#46dc02",
      "course": "Biology",
      "favorite": false
    },
    {
      "id": "77c91e76-9b2a-4d05-9fd8-f89042d38b3a",
      "full_name": "Oliver Mortensen",
      "gender": "Male",
      "b_date": "1967-08-12",
      "age": 58,
      "email": "oliver.mortensen@example.com",
      "phone": "03180365",
      "country": "Denmark",
      "city": "Sommersted",
      "latitude": "61.8343",
      "longitude": "-159.9565",
      "picture_large": "https://randomuser.me/api/portraits/men/95.jpg",
      "note": "Note1...",
      "color": "#af622e",
      "course": "Dancing",
      "favorite": false
    },
    {
      "id": "b8ee4af7-9b50-434f-850f-ab16be7bbe19",
      "full_name": "Jerónimo Sotelo",
      "gender": "Male",
      "b_date": "1974-11-04",
      "age": 50,
      "email": "jeronimo.sotelo@example.com",
      "phone": "(695) 505 3398",
      "country": "Mexico",
      "city": "San Bartolo Coyotepec",
      "latitude": "84.3689",
      "longitude": "-17.1015",
      "picture_large": "https://randomuser.me/api/portraits/men/10.jpg",
      "note": "Note1...",
      "color": "#3cd629",
      "course": "Art",
      "favorite": true
    },
    {
      "id": "c8fa5e48-73b6-494b-a5a0-a139c6a66f9e",
      "full_name": "Arianna Carpentier",
      "gender": "Female",
      "b_date": "1966-06-25",
      "age": 59,
      "email": "arianna.carpentier@example.com",
      "phone": "077 717 84 36",
      "country": "Switzerland",
      "city": "Fläsch",
      "latitude": "37.0252",
      "longitude": "151.6329",
      "picture_large": "https://randomuser.me/api/portraits/women/16.jpg",
      "note": "Note1...",
      "color": "#6d99c3",
      "course": "Chemistry",
      "favorite": true
    },
    {
      "id": "186a13bd-a14d-4353-b4ba-ff38d816559c",
      "full_name": "Kahaan Gamskar",
      "gender": "Male",
      "b_date": "1987-03-10",
      "age": 38,
      "email": "kahaan.gamskar@example.com",
      "phone": "7307100725",
      "country": "India",
      "city": "Kumbakonam",
      "latitude": "13.4004",
      "longitude": "-93.0716",
      "picture_large": "https://randomuser.me/api/portraits/men/82.jpg",
      "note": "Note1...",
      "color": "#d78f08",
      "course": "Art",
      "favorite": false
    },
    {
      "id": "e77d8904-ef0d-413f-940a-f156aa26c120",
      "full_name": "Onufriy Mudrik",
      "gender": "Male",
      "b_date": "1964-03-30",
      "age": 61,
      "email": "onufriy.mudrik@example.com",
      "phone": "(068) J56-9285",
      "country": "Ukraine",
      "city": "Truskavec",
      "latitude": "-48.2646",
      "longitude": "-44.2434",
      "picture_large": "https://randomuser.me/api/portraits/men/70.jpg",
      "note": "Note1...",
      "color": "#a91b18",
      "course": "Art",
      "favorite": false
    },
    {
      "id": "bc37e50f-a496-4038-8ce3-cd591f99b060",
      "full_name": "Martin Ferguson",
      "gender": "Male",
      "b_date": "1981-08-20",
      "age": 44,
      "email": "martin.ferguson@example.com",
      "phone": "08-5706-2681",
      "country": "Australia",
      "city": "Traralgon",
      "latitude": "39.9035",
      "longitude": "55.0055",
      "picture_large": "https://randomuser.me/api/portraits/men/2.jpg",
      "note": "Note1...",
      "color": "#3a7d64",
      "course": "Art",
      "favorite": true
    },
    {
      "id": "ad4818c1-2a50-4cb1-a62f-61e19f5076f4",
      "full_name": "Ratimir Loboyko",
      "gender": "Male",
      "b_date": "1951-08-22",
      "age": 74,
      "email": "ratimir.loboyko@example.com",
      "phone": "(098) Z70-3125",
      "country": "Ukraine",
      "city": "Vovchansk",
      "latitude": "34.9283",
      "longitude": "133.5735",
      "picture_large": "https://randomuser.me/api/portraits/men/49.jpg",
      "note": "Note1...",
      "color": "#6ec222",
      "course": "Biology",
      "favorite": false
    },
    {
      "id": "f25a6567-6519-4b4a-b49a-734f3a1bce9a",
      "full_name": "Jesse Mcguinness",
      "gender": "Male",
      "b_date": "1965-07-10",
      "age": 60,
      "email": "jesse.mcguinness@example.com",
      "phone": "011-098-4914",
      "country": "Ireland",
      "city": "Carrickmacross",
      "latitude": "-72.1417",
      "longitude": "84.4417",
      "picture_large": "https://randomuser.me/api/portraits/men/26.jpg",
      "note": "Note1...",
      "color": "#4d03b6",
      "course": "Biology",
      "favorite": false
    },
    {
      "id": "03c3e100-2491-42a3-859c-924910d3df41",
      "full_name": "Rui Thomas",
      "gender": "Male",
      "b_date": "1969-08-22",
      "age": 56,
      "email": "rui.thomas@example.com",
      "phone": "076 892 54 22",
      "country": "Switzerland",
      "city": "Müllheim",
      "latitude": "-13.0093",
      "longitude": "-22.7616",
      "picture_large": "https://randomuser.me/api/portraits/men/98.jpg",
      "note": "Note1...",
      "color": "#ea2101",
      "course": "English",
      "favorite": false
    },
    {
      "id": "658e415b-5d56-4edc-8475-bb874e04dca3",
      "full_name": "Pamela Silva",
      "gender": "Female",
      "b_date": "1968-02-01",
      "age": 57,
      "email": "pamela.silva@example.com",
      "phone": "(739) 940-3899",
      "country": "United States",
      "city": "Evansville",
      "latitude": "-16.8707",
      "longitude": "161.7034",
      "picture_large": "https://randomuser.me/api/portraits/women/72.jpg",
      "note": "Note1...",
      "color": "#a08915",
      "course": "Chemistry",
      "favorite": false
    },
    {
      "id": "39f7c8cd-d943-4394-aadb-8254fb153635",
      "full_name": "Irena Lechner",
      "gender": "Female",
      "b_date": "1986-12-21",
      "age": 38,
      "email": "irena.lechner@example.com",
      "phone": "0003-1854896",
      "country": "Germany",
      "city": "Radevormwald",
      "latitude": "-25.6323",
      "longitude": "17.0444",
      "picture_large": "https://randomuser.me/api/portraits/women/92.jpg",
      "note": "Note1...",
      "color": "#c662b2",
      "course": "Art",
      "favorite": true
    },
    {
      "id": "62021d25-221e-40bc-a37e-44bf3a3f36a6",
      "full_name": "Mackenzie Harris",
      "gender": "Female",
      "b_date": "1980-12-07",
      "age": 44,
      "email": "mackenzie.harris@example.com",
      "phone": "(612)-265-4335",
      "country": "New Zealand",
      "city": "Hastings",
      "latitude": "-51.3730",
      "longitude": "117.4381",
      "picture_large": "https://randomuser.me/api/portraits/women/85.jpg",
      "note": "Note1...",
      "color": "#6a8df0",
      "course": "English",
      "favorite": false
    },
    {
      "id": "66461329-897c-4f85-84ae-4a05f415b828",
      "full_name": "Sandra Zarate",
      "gender": "Female",
      "b_date": "1962-11-25",
      "age": 62,
      "email": "sandra.zarate@example.com",
      "phone": "(661) 223 5055",
      "country": "Mexico",
      "city": "Perote",
      "latitude": "60.3710",
      "longitude": "26.4650",
      "picture_large": "https://randomuser.me/api/portraits/women/77.jpg",
      "note": "Note1...",
      "color": "#688c03",
      "course": "Law",
      "favorite": false
    },
    {
      "id": "57e86f60-eda1-4d79-86d8-abec5d4e4911",
      "full_name": "Lidia Carmona",
      "gender": "Female",
      "b_date": "2000-04-02",
      "age": 25,
      "email": "lidia.carmona@example.com",
      "phone": "998-769-364",
      "country": "Spain",
      "city": "Parla",
      "latitude": "4.2009",
      "longitude": "-65.3617",
      "picture_large": "https://randomuser.me/api/portraits/women/71.jpg",
      "note": "Note1...",
      "color": "#c89b8d",
      "course": "Physics",
      "favorite": false
    },
    {
      "id": "510de6ee-83de-4e76-8737-66c97d40d03d",
      "full_name": "Angela Morgan",
      "gender": "Female",
      "b_date": "1971-02-21",
      "age": 54,
      "email": "angela.morgan@example.com",
      "phone": "017684 41062",
      "country": "United Kingdom",
      "city": "Preston",
      "latitude": "-0.6107",
      "longitude": "61.3111",
      "picture_large": "https://randomuser.me/api/portraits/women/87.jpg",
      "note": "Note1...",
      "color": "#870ec5",
      "course": "Dancing",
      "favorite": false
    },
    {
      "id": "ae700916-c49e-4e5c-9328-04a38674ea01",
      "full_name": "Tamara Fowler",
      "gender": "Female",
      "b_date": "1948-04-10",
      "age": 77,
      "email": "tamara.fowler@example.com",
      "phone": "(689) 465-7345",
      "country": "United States",
      "city": "Palmdale",
      "latitude": "-65.5782",
      "longitude": "61.4724",
      "picture_large": "https://randomuser.me/api/portraits/women/82.jpg",
      "note": "Note1...",
      "color": "#225fba",
      "course": "Biology",
      "favorite": false
    },
    {
      "id": "2dcfc131-0499-43bf-8cd6-aace8baecc04",
      "full_name": "Arpitha Dsouza",
      "gender": "Female",
      "b_date": "1965-03-12",
      "age": 60,
      "email": "arpitha.dsouza@example.com",
      "phone": "8415252881",
      "country": "India",
      "city": "Bhiwandi",
      "latitude": "14.1844",
      "longitude": "-147.8978",
      "picture_large": "https://randomuser.me/api/portraits/women/67.jpg",
      "note": "Note1...",
      "color": "#e483e5",
      "course": "Mathematics",
      "favorite": false
    },
    {
      "id": "14c305c9-b66b-4ee1-810b-154b4a6f2450",
      "full_name": "Leevi Ollila",
      "gender": "Male",
      "b_date": "1992-09-03",
      "age": 33,
      "email": "leevi.ollila@example.com",
      "phone": "04-237-592",
      "country": "Finland",
      "city": "Paimio",
      "latitude": "2.3663",
      "longitude": "-124.7140",
      "picture_large": "https://randomuser.me/api/portraits/men/84.jpg",
      "note": "Note1...",
      "color": "#792dcc",
      "course": "Computer Science",
      "favorite": false
    },
    {
      "id": "63415c35-b156-4bd2-854b-7087a08be7a0",
      "full_name": "Paul Pierce",
      "gender": "Male",
      "b_date": "1978-03-04",
      "age": 47,
      "email": "paul.pierce@example.com",
      "phone": "(395) 540-7438",
      "country": "United States",
      "city": "Cedar Rapids",
      "latitude": "-29.8129",
      "longitude": "-86.8181",
      "picture_large": "https://randomuser.me/api/portraits/men/51.jpg",
      "note": "Note1...",
      "color": "#3cd4f7",
      "course": "English",
      "favorite": true
    },
    {
      "id": "52916ac8-c42b-4828-9ccb-7f6908c4c835",
      "full_name": "Hector Sanchez",
      "gender": "Male",
      "b_date": "1945-04-18",
      "age": 80,
      "email": "hector.sanchez@example.com",
      "phone": "04-97-59-73-11",
      "country": "France",
      "city": "Grenoble",
      "latitude": "72.4172",
      "longitude": "-30.3796",
      "picture_large": "https://randomuser.me/api/portraits/men/51.jpg",
      "note": "Note1...",
      "color": "#5b772c",
      "course": "Medicine",
      "favorite": false
    },
    {
      "id": "f162e05a-806a-454c-abd9-24a67d5d3a53",
      "full_name": "Carl Møller",
      "gender": "Male",
      "b_date": "1956-07-22",
      "age": 69,
      "email": "carl.moller@example.com",
      "phone": "01888860",
      "country": "Denmark",
      "city": "Saltum",
      "latitude": "-17.1777",
      "longitude": "136.2169",
      "picture_large": "https://randomuser.me/api/portraits/men/60.jpg",
      "note": "Note1...",
      "color": "#051aa0",
      "course": "Chess",
      "favorite": false
    }
  ],
  "displayedUsers": [
    {
      "id": "ac4269e4-a4fb-4954-adc9-19eca4c43f6d",
      "full_name": "مریم پارسا",
      "gender": "Female",
      "b_date": "1994-05-18",
      "age": 31,
      "email": "mrym.prs@example.com",
      "phone": "037-32948611",
      "country": "Iran",
      "city": "کرمان",
      "latitude": "16.4145",
      "longitude": "31.2260",
      "picture_large": "https://randomuser.me/api/portraits/women/61.jpg",
      "note": "Note1...",
      "color": "#52bf85",
      "course": "Statistics",
      "favorite": false
    },
    {
      "id": "00f89564-e923-4957-922d-9a9ee9cd15bc",
      "full_name": "Diogo Peixoto",
      "gender": "Male",
      "b_date": "1984-05-12",
      "age": 41,
      "email": "diogo.peixoto@example.com",
      "phone": "(37) 8153-2740",
      "country": "Brazil",
      "city": "Várzea Paulista",
      "latitude": "-66.5348",
      "longitude": "176.1334",
      "picture_large": "https://randomuser.me/api/portraits/men/35.jpg",
      "note": "Note1...",
      "color": "#46dc02",
      "course": "Biology",
      "favorite": false
    },
    {
      "id": "1d09271c-b80d-409a-a4c7-da4176ec4880",
      "full_name": "Adna Moraes",
      "gender": "Female",
      "b_date": "1993-12-30",
      "age": 31,
      "email": "adna.moraes@example.com",
      "phone": "(16) 5360-0193",
      "country": "Brazil",
      "city": "João Pessoa",
      "latitude": "32.3396",
      "longitude": "-114.9154",
      "picture_large": "https://randomuser.me/api/portraits/women/73.jpg",
      "note": "Note1...",
      "color": "#bd9a41",
      "course": "Law",
      "favorite": false
    },
    {
      "id": "77c91e76-9b2a-4d05-9fd8-f89042d38b3a",
      "full_name": "Oliver Mortensen",
      "gender": "Male",
      "b_date": "1967-08-12",
      "age": 58,
      "email": "oliver.mortensen@example.com",
      "phone": "03180365",
      "country": "Denmark",
      "city": "Sommersted",
      "latitude": "61.8343",
      "longitude": "-159.9565",
      "picture_large": "https://randomuser.me/api/portraits/men/95.jpg",
      "note": "Note1...",
      "color": "#af622e",
      "course": "Dancing",
      "favorite": false
    },
    {
      "id": "d6c2995a-001f-45c0-8314-7d7151af53f1",
      "full_name": "Buse Koçoğlu",
      "gender": "Female",
      "b_date": "1948-01-22",
      "age": 77,
      "email": "buse.kocoglu@example.com",
      "phone": "(432)-755-4245",
      "country": "Turkey",
      "city": "Adıyaman",
      "latitude": "67.4825",
      "longitude": "26.2511",
      "picture_large": "https://randomuser.me/api/portraits/women/78.jpg",
      "note": "Note1...",
      "color": "#c512e3",
      "course": "Chess",
      "favorite": false
    },
    {
      "id": "b8ee4af7-9b50-434f-850f-ab16be7bbe19",
      "full_name": "Jerónimo Sotelo",
      "gender": "Male",
      "b_date": "1974-11-04",
      "age": 50,
      "email": "jeronimo.sotelo@example.com",
      "phone": "(695) 505 3398",
      "country": "Mexico",
      "city": "San Bartolo Coyotepec",
      "latitude": "84.3689",
      "longitude": "-17.1015",
      "picture_large": "https://randomuser.me/api/portraits/men/10.jpg",
      "note": "Note1...",
      "color": "#3cd629",
      "course": "Art",
      "favorite": true
    },
    {
      "id": "14c305c9-b66b-4ee1-810b-154b4a6f2450",
      "full_name": "Leevi Ollila",
      "gender": "Male",
      "b_date": "1992-09-03",
      "age": 33,
      "email": "leevi.ollila@example.com",
      "phone": "04-237-592",
      "country": "Finland",
      "city": "Paimio",
      "latitude": "2.3663",
      "longitude": "-124.7140",
      "picture_large": "https://randomuser.me/api/portraits/men/84.jpg",
      "note": "Note1...",
      "color": "#792dcc",
      "course": "Computer Science",
      "favorite": false
    },
    {
      "id": "63415c35-b156-4bd2-854b-7087a08be7a0",
      "full_name": "Paul Pierce",
      "gender": "Male",
      "b_date": "1978-03-04",
      "age": 47,
      "email": "paul.pierce@example.com",
      "phone": "(395) 540-7438",
      "country": "United States",
      "city": "Cedar Rapids",
      "latitude": "-29.8129",
      "longitude": "-86.8181",
      "picture_large": "https://randomuser.me/api/portraits/men/51.jpg",
      "note": "Note1...",
      "color": "#3cd4f7",
      "course": "English",
      "favorite": true
    },
    {
      "id": "52916ac8-c42b-4828-9ccb-7f6908c4c835",
      "full_name": "Hector Sanchez",
      "gender": "Male",
      "b_date": "1945-04-18",
      "age": 80,
      "email": "hector.sanchez@example.com",
      "phone": "04-97-59-73-11",
      "country": "France",
      "city": "Grenoble",
      "latitude": "72.4172",
      "longitude": "-30.3796",
      "picture_large": "https://randomuser.me/api/portraits/men/51.jpg",
      "note": "Note1...",
      "color": "#5b772c",
      "course": "Medicine",
      "favorite": false
    },
    {
      "id": "fef28e9f-5057-4482-a402-7a36e05d754b",
      "full_name": "Ross Mckinney",
      "gender": "Male",
      "b_date": "1961-07-29",
      "age": 64,
      "email": "ross.mckinney@example.com",
      "phone": "05-4055-7194",
      "country": "Australia",
      "city": "Hervey Bay",
      "latitude": "-61.6385",
      "longitude": "-48.4668",
      "picture_large": "https://randomuser.me/api/portraits/men/45.jpg",
      "note": "Note1...",
      "color": "#447936",
      "course": "Chemistry",
      "favorite": true
    },
    {
      "id": "f162e05a-806a-454c-abd9-24a67d5d3a53",
      "full_name": "Carl Møller",
      "gender": "Male",
      "b_date": "1956-07-22",
      "age": 69,
      "email": "carl.moller@example.com",
      "phone": "01888860",
      "country": "Denmark",
      "city": "Saltum",
      "latitude": "-17.1777",
      "longitude": "136.2169",
      "picture_large": "https://randomuser.me/api/portraits/men/60.jpg",
      "note": "Note1...",
      "color": "#051aa0",
      "course": "Chess",
      "favorite": false
    },
    {
      "id": "6d82bbca-2881-41f8-8094-5fea8f5c3d28",
      "full_name": "Linda Roberts",
      "gender": "Female",
      "b_date": "1980-03-25",
      "age": 45,
      "email": "linda.roberts@example.com",
      "phone": "(926) 724-9868",
      "country": "United States",
      "city": "Pittsburgh",
      "latitude": "-40.0918",
      "longitude": "9.2141",
      "picture_large": "https://randomuser.me/api/portraits/women/6.jpg",
      "note": "Note1...",
      "color": "#f051ae",
      "course": "Chess",
      "favorite": false
    },
    {
      "id": "b54c401e-3507-4a61-b901-dabac80a0a15",
      "full_name": "Ellen Linna",
      "gender": "Female",
      "b_date": "1970-08-04",
      "age": 55,
      "email": "ellen.linna@example.com",
      "phone": "03-275-393",
      "country": "Finland",
      "city": "Akaa",
      "latitude": "-60.9073",
      "longitude": "126.7213",
      "picture_large": "https://randomuser.me/api/portraits/women/36.jpg",
      "note": "Note1...",
      "color": "#ec6e7d",
      "course": "Medicine",
      "favorite": true
    },
    {
      "id": "d445c8e4-014b-4d29-bc0b-f2cbc2b265e6",
      "full_name": "Élise Henry",
      "gender": "Female",
      "b_date": "1989-10-03",
      "age": 36,
      "email": "elise.henry@example.com",
      "phone": "079 942 19 85",
      "country": "Switzerland",
      "city": "Küssnacht (Sz)",
      "latitude": "62.3097",
      "longitude": "92.2200",
      "picture_large": "https://randomuser.me/api/portraits/women/92.jpg",
      "note": "Note1...",
      "color": "#ac1871",
      "course": "Chess",
      "favorite": true
    },
    {
      "id": "624498c1-9c83-4f87-a1b7-5cebda0e966e",
      "full_name": "Necati Ertürk",
      "gender": "Male",
      "b_date": "1998-05-21",
      "age": 27,
      "email": "necati.erturk@example.com",
      "phone": "(582)-567-7286",
      "country": "Turkey",
      "city": "Zonguldak",
      "latitude": "71.5483",
      "longitude": "-165.8365",
      "picture_large": "https://randomuser.me/api/portraits/men/48.jpg",
      "note": "Note1...",
      "color": "#730947",
      "course": "Physics",
      "favorite": false
    },
    {
      "id": "23cf0656-55fd-4735-afde-d1ebc0062609",
      "full_name": "Nihal Akar",
      "gender": "Male",
      "b_date": "1981-01-02",
      "age": 44,
      "email": "nihal.akar@example.com",
      "phone": "(380)-887-8357",
      "country": "Turkey",
      "city": "Bursa",
      "latitude": "-11.6535",
      "longitude": "-113.7978",
      "picture_large": "https://randomuser.me/api/portraits/men/24.jpg",
      "note": "Note1...",
      "color": "#ab1431",
      "course": "Physics",
      "favorite": false
    },
    {
      "id": "eb8fc623-c926-4c78-bb5e-4e695432905c",
      "full_name": "Katerina Slota",
      "gender": "Female",
      "b_date": "1970-08-30",
      "age": 55,
      "email": "katerina.slota@example.com",
      "phone": "(066) B68-4113",
      "country": "Ukraine",
      "city": "Pervomayskiy",
      "latitude": "3.2454",
      "longitude": "101.0270",
      "picture_large": "https://randomuser.me/api/portraits/women/9.jpg",
      "note": "Note1...",
      "color": "#cc133f",
      "course": "Statistics",
      "favorite": false
    },
    {
      "id": "6479e824-6faf-4550-8d97-2d7b2d921b53",
      "full_name": "Snežana Radosavljević",
      "gender": "Female",
      "b_date": "1956-08-28",
      "age": 69,
      "email": "snezana.radosavljevic@example.com",
      "phone": "037-7891-900",
      "country": "Serbia",
      "city": "Topola",
      "latitude": "1.3469",
      "longitude": "14.4756",
      "picture_large": "https://randomuser.me/api/portraits/women/58.jpg",
      "note": "Note1...",
      "color": "#61658f",
      "course": "Chemistry",
      "favorite": false
    },
    {
      "id": "9ce2b109-db25-443e-903e-ece90f40b018",
      "full_name": "Ludwig Rolland",
      "gender": "Male",
      "b_date": "1964-05-07",
      "age": 61,
      "email": "ludwig.rolland@example.com",
      "phone": "075 944 62 61",
      "country": "Switzerland",
      "city": "Menziken",
      "latitude": "38.4919",
      "longitude": "99.7481",
      "picture_large": "https://randomuser.me/api/portraits/men/10.jpg",
      "note": "Note1...",
      "color": "#4f12ae",
      "course": "Dancing",
      "favorite": true
    },
    {
      "id": "0fcff9ce-4e9a-4612-a295-1791248a61e4",
      "full_name": "Babür Karaböcek",
      "gender": "Male",
      "b_date": "1968-09-27",
      "age": 57,
      "email": "babur.karabocek@example.com",
      "phone": "(057)-817-4745",
      "country": "Turkey",
      "city": "Eskişehir",
      "latitude": "-43.0271",
      "longitude": "-102.8575",
      "picture_large": "https://randomuser.me/api/portraits/men/66.jpg",
      "note": "Note1...",
      "color": "#269490",
      "course": "Mathematics",
      "favorite": false
    },
    {
      "id": "37fc9d50-bd47-4e8e-9c5e-133094582840",
      "full_name": "Calvino Rezende",
      "gender": "Male",
      "b_date": "1983-06-22",
      "age": 42,
      "email": "calvino.rezende@example.com",
      "phone": "(19) 7414-1735",
      "country": "Brazil",
      "city": "Carapicuíba",
      "latitude": "24.8663",
      "longitude": "85.7904",
      "picture_large": "https://randomuser.me/api/portraits/men/42.jpg",
      "note": "Note1...",
      "color": "#d850df",
      "course": "Medicine",
      "favorite": true
    },
    {
      "id": "07d9a7f2-adbf-42e5-b763-3b85f58947f2",
      "full_name": "Bozena Habermann",
      "gender": "Female",
      "b_date": "1998-01-16",
      "age": 27,
      "email": "bozena.habermann@example.com",
      "phone": "0825-4273527",
      "country": "Germany",
      "city": "Treuen",
      "latitude": "-56.8439",
      "longitude": "168.6799",
      "picture_large": "https://randomuser.me/api/portraits/women/31.jpg",
      "note": "Note1...",
      "color": "#cabd0b",
      "course": "English",
      "favorite": false
    },
    {
      "id": "50c29474-add7-4128-8dbf-2642244c4fe2",
      "full_name": "Tony Lemoine",
      "gender": "Male",
      "b_date": "2000-03-02",
      "age": 25,
      "email": "tony.lemoine@example.com",
      "phone": "04-99-25-85-14",
      "country": "France",
      "city": "Argenteuil",
      "latitude": "68.9488",
      "longitude": "82.4233",
      "picture_large": "https://randomuser.me/api/portraits/men/71.jpg",
      "note": "Note1...",
      "color": "#e31f9f",
      "course": "Dancing",
      "favorite": true
    },
    {
      "id": "742fd88e-11ea-43aa-a3c0-46020d2b6281",
      "full_name": "Arianna Fields",
      "gender": "Female",
      "b_date": "1986-07-05",
      "age": 39,
      "email": "arianna.fields@example.com",
      "phone": "04-9309-6264",
      "country": "Australia",
      "city": "Perth",
      "latitude": "58.9362",
      "longitude": "144.0388",
      "picture_large": "https://randomuser.me/api/portraits/women/19.jpg",
      "note": "Note1...",
      "color": "#48c4d0",
      "course": "English",
      "favorite": false
    },
    {
      "id": "fc31f880-806f-4cf6-b8d4-8abb3dabda74",
      "full_name": "Sophia Nguyen",
      "gender": "Female",
      "b_date": "1951-08-09",
      "age": 74,
      "email": "sophia.nguyen@example.com",
      "phone": "05-9304-4920",
      "country": "Australia",
      "city": "Mackay",
      "latitude": "58.6600",
      "longitude": "63.0624",
      "picture_large": "https://randomuser.me/api/portraits/women/11.jpg",
      "note": "Note1...",
      "color": "#4aee5a",
      "course": "Chemistry",
      "favorite": true
    },
    {
      "id": "4a1e3c08-2031-4aa2-8ac5-13f20ba736e0",
      "full_name": "Navami Chavare",
      "gender": "Female",
      "b_date": "1946-01-24",
      "age": 79,
      "email": "navami.chavare@example.com",
      "phone": "8116253686",
      "country": "India",
      "city": "Bareilly",
      "latitude": "38.2106",
      "longitude": "117.6904",
      "picture_large": "https://randomuser.me/api/portraits/women/27.jpg",
      "note": "Note1...",
      "color": "#98981d",
      "course": "English",
      "favorite": false
    },
    {
      "id": "69f43796-098b-41e7-91ee-779bc3296e55",
      "full_name": "فاطمه کوتی",
      "gender": "Female",
      "b_date": "1984-04-18",
      "age": 41,
      "email": "ftmh.khwty@example.com",
      "phone": "080-36985956",
      "country": "Iran",
      "city": "ارومیه",
      "latitude": "-15.6883",
      "longitude": "7.9130",
      "picture_large": "https://randomuser.me/api/portraits/women/62.jpg",
      "note": "Note1...",
      "color": "#d5dda0",
      "course": "Chemistry",
      "favorite": false
    },
    {
      "id": "bd58bc06-3fc7-4c89-bc6c-5702ad9a011c",
      "full_name": "Fatih Çetiner",
      "gender": "Male",
      "b_date": "1964-12-11",
      "age": 60,
      "email": "fatih.cetiner@example.com",
      "phone": "(694)-758-8852",
      "country": "Turkey",
      "city": "Erzurum",
      "latitude": "56.9364",
      "longitude": "132.5903",
      "picture_large": "https://randomuser.me/api/portraits/men/23.jpg",
      "note": "Note1...",
      "color": "#507da5",
      "course": "Dancing",
      "favorite": true
    },
    {
      "id": "ddc92074-d06f-49ea-816c-cad0369ecbef",
      "full_name": "Nelson Lawson",
      "gender": "Male",
      "b_date": "1984-02-04",
      "age": 41,
      "email": "nelson.lawson@example.com",
      "phone": "(784) 778-1551",
      "country": "United States",
      "city": "Oklahoma City",
      "latitude": "2.4149",
      "longitude": "96.3089",
      "picture_large": "https://randomuser.me/api/portraits/men/42.jpg",
      "note": "Note1...",
      "color": "#b06ff9",
      "course": "Chess",
      "favorite": false
    },
    {
      "id": "ad4ee7c1-119d-4712-9e34-29c51279ec7c",
      "full_name": "Väinö Pulli",
      "gender": "Male",
      "b_date": "1950-01-05",
      "age": 75,
      "email": "vaino.pulli@example.com",
      "phone": "07-762-493",
      "country": "Finland",
      "city": "Kustavi",
      "latitude": "-83.6229",
      "longitude": "-16.2593",
      "picture_large": "https://randomuser.me/api/portraits/men/2.jpg",
      "note": "Note1...",
      "color": "#3d8d78",
      "course": "Chess",
      "favorite": false
    },
    {
      "id": "7dc4c650-dd1f-4153-951f-7793920f81eb",
      "full_name": "Kaća Mihajlović",
      "gender": "Female",
      "b_date": "1947-04-14",
      "age": 78,
      "email": "kaca.mihajlovic@example.com",
      "phone": "011-3751-553",
      "country": "Serbia",
      "city": "Bujanovac",
      "latitude": "9.2021",
      "longitude": "42.4591",
      "picture_large": "https://randomuser.me/api/portraits/women/95.jpg",
      "note": "Note1...",
      "color": "#c3aea5",
      "course": "Statistics",
      "favorite": false
    },
    {
      "id": "b09ee84f-a3e5-4177-9259-483488efa9d3",
      "full_name": "Nevena Simeonović",
      "gender": "Female",
      "b_date": "1996-02-26",
      "age": 29,
      "email": "nevena.simeonovic@example.com",
      "phone": "039-9430-414",
      "country": "Serbia",
      "city": "Knić",
      "latitude": "41.8849",
      "longitude": "89.2096",
      "picture_large": "https://randomuser.me/api/portraits/women/20.jpg",
      "note": "Note1...",
      "color": "#8c3b77",
      "course": "English",
      "favorite": false
    },
    {
      "id": "4a19cd2b-6c68-48d0-abd8-6e8163dab93c",
      "full_name": "Larry Bishop",
      "gender": "Male",
      "b_date": "1972-10-17",
      "age": 53,
      "email": "larry.bishop@example.com",
      "phone": "06-0050-1879",
      "country": "Australia",
      "city": "Melbourne",
      "latitude": "-0.8933",
      "longitude": "-27.1955",
      "picture_large": "https://randomuser.me/api/portraits/men/93.jpg",
      "note": "Note1...",
      "color": "#ab4e95",
      "course": "English",
      "favorite": false
    },
    {
      "id": "ccbd4ade-ddba-4562-bc61-71c5937bca19",
      "full_name": "Rosina Opanasenko",
      "gender": "Female",
      "b_date": "1963-09-06",
      "age": 62,
      "email": "rosina.opanasenko@example.com",
      "phone": "(099) L68-1974",
      "country": "Ukraine",
      "city": "Derazhnya",
      "latitude": "36.9575",
      "longitude": "-31.2198",
      "picture_large": "https://randomuser.me/api/portraits/women/93.jpg",
      "note": "Note1...",
      "color": "#274c75",
      "course": "Chess",
      "favorite": true
    },
    {
      "id": "2ca3a611-7170-43a2-8e80-1dd7892d4d31",
      "full_name": "Berta Fogaça",
      "gender": "Female",
      "b_date": "1996-07-22",
      "age": 29,
      "email": "berta.fogaca@example.com",
      "phone": "(38) 5637-1045",
      "country": "Brazil",
      "city": "Belford Roxo",
      "latitude": "-1.0856",
      "longitude": "123.9201",
      "picture_large": "https://randomuser.me/api/portraits/women/13.jpg",
      "note": "Note1...",
      "color": "#709239",
      "course": "Law",
      "favorite": true
    },
    {
      "id": "c8fa5e48-73b6-494b-a5a0-a139c6a66f9e",
      "full_name": "Arianna Carpentier",
      "gender": "Female",
      "b_date": "1966-06-25",
      "age": 59,
      "email": "arianna.carpentier@example.com",
      "phone": "077 717 84 36",
      "country": "Switzerland",
      "city": "Fläsch",
      "latitude": "37.0252",
      "longitude": "151.6329",
      "picture_large": "https://randomuser.me/api/portraits/women/16.jpg",
      "note": "Note1...",
      "color": "#6d99c3",
      "course": "Chemistry",
      "favorite": true
    },
    {
      "id": "186a13bd-a14d-4353-b4ba-ff38d816559c",
      "full_name": "Kahaan Gamskar",
      "gender": "Male",
      "b_date": "1987-03-10",
      "age": 38,
      "email": "kahaan.gamskar@example.com",
      "phone": "7307100725",
      "country": "India",
      "city": "Kumbakonam",
      "latitude": "13.4004",
      "longitude": "-93.0716",
      "picture_large": "https://randomuser.me/api/portraits/men/82.jpg",
      "note": "Note1...",
      "color": "#d78f08",
      "course": "Art",
      "favorite": false
    },
    {
      "id": "e77d8904-ef0d-413f-940a-f156aa26c120",
      "full_name": "Onufriy Mudrik",
      "gender": "Male",
      "b_date": "1964-03-30",
      "age": 61,
      "email": "onufriy.mudrik@example.com",
      "phone": "(068) J56-9285",
      "country": "Ukraine",
      "city": "Truskavec",
      "latitude": "-48.2646",
      "longitude": "-44.2434",
      "picture_large": "https://randomuser.me/api/portraits/men/70.jpg",
      "note": "Note1...",
      "color": "#a91b18",
      "course": "Art",
      "favorite": false
    },
    {
      "id": "bc37e50f-a496-4038-8ce3-cd591f99b060",
      "full_name": "Martin Ferguson",
      "gender": "Male",
      "b_date": "1981-08-20",
      "age": 44,
      "email": "martin.ferguson@example.com",
      "phone": "08-5706-2681",
      "country": "Australia",
      "city": "Traralgon",
      "latitude": "39.9035",
      "longitude": "55.0055",
      "picture_large": "https://randomuser.me/api/portraits/men/2.jpg",
      "note": "Note1...",
      "color": "#3a7d64",
      "course": "Art",
      "favorite": true
    },
    {
      "id": "ad4818c1-2a50-4cb1-a62f-61e19f5076f4",
      "full_name": "Ratimir Loboyko",
      "gender": "Male",
      "b_date": "1951-08-22",
      "age": 74,
      "email": "ratimir.loboyko@example.com",
      "phone": "(098) Z70-3125",
      "country": "Ukraine",
      "city": "Vovchansk",
      "latitude": "34.9283",
      "longitude": "133.5735",
      "picture_large": "https://randomuser.me/api/portraits/men/49.jpg",
      "note": "Note1...",
      "color": "#6ec222",
      "course": "Biology",
      "favorite": false
    },
    {
      "id": "f25a6567-6519-4b4a-b49a-734f3a1bce9a",
      "full_name": "Jesse Mcguinness",
      "gender": "Male",
      "b_date": "1965-07-10",
      "age": 60,
      "email": "jesse.mcguinness@example.com",
      "phone": "011-098-4914",
      "country": "Ireland",
      "city": "Carrickmacross",
      "latitude": "-72.1417",
      "longitude": "84.4417",
      "picture_large": "https://randomuser.me/api/portraits/men/26.jpg",
      "note": "Note1...",
      "color": "#4d03b6",
      "course": "Biology",
      "favorite": false
    },
    {
      "id": "03c3e100-2491-42a3-859c-924910d3df41",
      "full_name": "Rui Thomas",
      "gender": "Male",
      "b_date": "1969-08-22",
      "age": 56,
      "email": "rui.thomas@example.com",
      "phone": "076 892 54 22",
      "country": "Switzerland",
      "city": "Müllheim",
      "latitude": "-13.0093",
      "longitude": "-22.7616",
      "picture_large": "https://randomuser.me/api/portraits/men/98.jpg",
      "note": "Note1...",
      "color": "#ea2101",
      "course": "English",
      "favorite": false
    },
    {
      "id": "658e415b-5d56-4edc-8475-bb874e04dca3",
      "full_name": "Pamela Silva",
      "gender": "Female",
      "b_date": "1968-02-01",
      "age": 57,
      "email": "pamela.silva@example.com",
      "phone": "(739) 940-3899",
      "country": "United States",
      "city": "Evansville",
      "latitude": "-16.8707",
      "longitude": "161.7034",
      "picture_large": "https://randomuser.me/api/portraits/women/72.jpg",
      "note": "Note1...",
      "color": "#a08915",
      "course": "Chemistry",
      "favorite": false
    },
    {
      "id": "39f7c8cd-d943-4394-aadb-8254fb153635",
      "full_name": "Irena Lechner",
      "gender": "Female",
      "b_date": "1986-12-21",
      "age": 38,
      "email": "irena.lechner@example.com",
      "phone": "0003-1854896",
      "country": "Germany",
      "city": "Radevormwald",
      "latitude": "-25.6323",
      "longitude": "17.0444",
      "picture_large": "https://randomuser.me/api/portraits/women/92.jpg",
      "note": "Note1...",
      "color": "#c662b2",
      "course": "Art",
      "favorite": true
    },
    {
      "id": "62021d25-221e-40bc-a37e-44bf3a3f36a6",
      "full_name": "Mackenzie Harris",
      "gender": "Female",
      "b_date": "1980-12-07",
      "age": 44,
      "email": "mackenzie.harris@example.com",
      "phone": "(612)-265-4335",
      "country": "New Zealand",
      "city": "Hastings",
      "latitude": "-51.3730",
      "longitude": "117.4381",
      "picture_large": "https://randomuser.me/api/portraits/women/85.jpg",
      "note": "Note1...",
      "color": "#6a8df0",
      "course": "English",
      "favorite": false
    },
    {
      "id": "66461329-897c-4f85-84ae-4a05f415b828",
      "full_name": "Sandra Zarate",
      "gender": "Female",
      "b_date": "1962-11-25",
      "age": 62,
      "email": "sandra.zarate@example.com",
      "phone": "(661) 223 5055",
      "country": "Mexico",
      "city": "Perote",
      "latitude": "60.3710",
      "longitude": "26.4650",
      "picture_large": "https://randomuser.me/api/portraits/women/77.jpg",
      "note": "Note1...",
      "color": "#688c03",
      "course": "Law",
      "favorite": false
    },
    {
      "id": "57e86f60-eda1-4d79-86d8-abec5d4e4911",
      "full_name": "Lidia Carmona",
      "gender": "Female",
      "b_date": "2000-04-02",
      "age": 25,
      "email": "lidia.carmona@example.com",
      "phone": "998-769-364",
      "country": "Spain",
      "city": "Parla",
      "latitude": "4.2009",
      "longitude": "-65.3617",
      "picture_large": "https://randomuser.me/api/portraits/women/71.jpg",
      "note": "Note1...",
      "color": "#c89b8d",
      "course": "Physics",
      "favorite": false
    },
    {
      "id": "510de6ee-83de-4e76-8737-66c97d40d03d",
      "full_name": "Angela Morgan",
      "gender": "Female",
      "b_date": "1971-02-21",
      "age": 54,
      "email": "angela.morgan@example.com",
      "phone": "017684 41062",
      "country": "United Kingdom",
      "city": "Preston",
      "latitude": "-0.6107",
      "longitude": "61.3111",
      "picture_large": "https://randomuser.me/api/portraits/women/87.jpg",
      "note": "Note1...",
      "color": "#870ec5",
      "course": "Dancing",
      "favorite": false
    },
    {
      "id": "ae700916-c49e-4e5c-9328-04a38674ea01",
      "full_name": "Tamara Fowler",
      "gender": "Female",
      "b_date": "1948-04-10",
      "age": 77,
      "email": "tamara.fowler@example.com",
      "phone": "(689) 465-7345",
      "country": "United States",
      "city": "Palmdale",
      "latitude": "-65.5782",
      "longitude": "61.4724",
      "picture_large": "https://randomuser.me/api/portraits/women/82.jpg",
      "note": "Note1...",
      "color": "#225fba",
      "course": "Biology",
      "favorite": false
    },
    {
      "id": "2dcfc131-0499-43bf-8cd6-aace8baecc04",
      "full_name": "Arpitha Dsouza",
      "gender": "Female",
      "b_date": "1965-03-12",
      "age": 60,
      "email": "arpitha.dsouza@example.com",
      "phone": "8415252881",
      "country": "India",
      "city": "Bhiwandi",
      "latitude": "14.1844",
      "longitude": "-147.8978",
      "picture_large": "https://randomuser.me/api/portraits/women/67.jpg",
      "note": "Note1...",
      "color": "#e483e5",
      "course": "Mathematics",
      "favorite": false
    }
  ]
}